[
  {
    "id": "tour_001",
    "name": "City Highlights Walking Tour",
    "basePrice": 45,
    "duration": "3 hours",
    "description": "Explore the main attractions of the city with a knowledgeable local guide",
    "categories": ["sightseeing", "walking", "culture"],
    "destinations": ["paris", "london", "rome", "all"],
    "source": "tripadvisor",
    "bookingUrl": "https://tripadvisor.com/tour/city-highlights",
    "rating": 4.6,
    "image": "https://images.unsplash.com/photo-1488646953014-85cb44e25828"
  },
  {
    "id": "tour_002",
    "name": "Food & Culture Tour",
    "basePrice": 75,
    "duration": "4 hours",
    "description": "Taste local cuisine and learn about the culture through food",
    "categories": ["food", "culture", "walking"],
    "destinations": ["tokyo", "bangkok", "paris", "all"],
    "source": "tripadvisor",
    "bookingUrl": "https://tripadvisor.com/tour/food-culture",
    "rating": 4.8,
    "image": "https://images.unsplash.com/photo-1504674900247-0877df9cc836"
  },
  {
    "id": "tour_003",
    "name": "Adventure Hiking Experience",
    "basePrice": 120,
    "duration": "Full day",
    "description": "Challenging hike through scenic trails with breathtaking views",
    "categories": ["adventure", "hiking", "nature"],
    "destinations": ["nepal", "switzerland", "all"],
    "source": "tripadvisor",
    "bookingUrl": "https://tripadvisor.com/tour/adventure-hiking",
    "rating": 4.7,
    "image": "https://images.unsplash.com/photo-1551632811-561732d1e306"
  },
  {
    "id": "tour_004",
    "name": "Sunset Cruise",
    "basePrice": 85,
    "duration": "2 hours",
    "description": "Relaxing boat cruise with stunning sunset views",
    "categories": ["relaxation", "scenic", "boat"],
    "destinations": ["bali", "maldives", "santorini", "all"],
    "source": "tripadvisor",
    "bookingUrl": "https://tripadvisor.com/tour/sunset-cruise",
    "rating": 4.5,
    "image": "https://images.unsplash.com/photo-1506905925346-21bda4d32df4"
  },
  {
    "id": "tour_005",
    "name": "Historical Museum Tour",
    "basePrice": 35,
    "duration": "2.5 hours",
    "description": "Guided tour through famous museums and historical sites",
    "categories": ["culture", "history", "museums"],
    "destinations": ["paris", "london", "rome", "vienna", "all"],
    "source": "tripadvisor",
    "bookingUrl": "https://tripadvisor.com/tour/museum-tour",
    "rating": 4.4,
    "image": "https://images.unsplash.com/photo-1578662996442-48f60103fc96"
  },
  {
    "id": "tour_006",
    "name": "Wildlife Safari",
    "basePrice": 150,
    "duration": "Full day",
    "description": "Experience wildlife in their natural habitat",
    "categories": ["adventure", "wildlife", "nature"],
    "destinations": ["kenya", "south africa", "all"],
    "source": "tripadvisor",
    "bookingUrl": "https://tripadvisor.com/tour/wildlife-safari",
    "rating": 4.9,
    "image": "https://images.unsplash.com/photo-1516426122078-c23e76319801"
  },
  {
    "id": "tour_007",
    "name": "Wine Tasting Experience",
    "basePrice": 95,
    "duration": "3 hours",
    "description": "Visit local vineyards and taste premium wines",
    "categories": ["food", "wine", "culture"],
    "destinations": ["france", "italy", "spain", "all"],
    "source": "tripadvisor",
    "bookingUrl": "https://tripadvisor.com/tour/wine-tasting",
    "rating": 4.6,
    "image": "https://images.unsplash.com/photo-1510812431401-41d2bd2722f3"
  },
  {
    "id": "tour_008",
    "name": "Photography Tour",
    "basePrice": 65,
    "duration": "4 hours",
    "description": "Capture the best shots with a professional photographer guide",
    "categories": ["photography", "sightseeing", "culture"],
    "destinations": ["all"],
    "source": "tripadvisor",
    "bookingUrl": "https://tripadvisor.com/tour/photography",
    "rating": 4.5,
    "image": "https://images.unsplash.com/photo-1502920917128-1aa500764cbd"
  },
  {
    "id": "tour_009",
    "name": "Bike Tour of the City",
    "basePrice": 55,
    "duration": "3 hours",
    "description": "Explore the city on two wheels with a local guide",
    "categories": ["adventure", "biking", "sightseeing"],
    "destinations": ["amsterdam", "copenhagen", "all"],
    "source": "tripadvisor",
    "bookingUrl": "https://tripadvisor.com/tour/bike-tour",
    "rating": 4.3,
    "image": "https://images.unsplash.com/photo-1558618666-fcd25c85cd64"
  },
  {
    "id": "tour_010",
    "name": "Cooking Class Experience",
    "basePrice": 80,
    "duration": "4 hours",
    "description": "Learn to cook traditional local dishes",
    "categories": ["food", "culture", "cooking"],
    "destinations": ["italy", "thailand", "japan", "all"],
    "source": "tripadvisor",
    "bookingUrl": "https://tripadvisor.com/tour/cooking-class",
    "rating": 4.7,
    "image": "https://images.unsplash.com/photo-1556910103-1c02745aae4d"
  }
]


